README.txt
setup.py
money/Money.py
money/__init__.py
money/django/__init__.py
money/django/forms/__init__.py
money/django/forms/fields.py
money/django/forms/widgets.py
money/django/models/__init__.py
money/django/models/fields.py
money/django/models/managers.py
python_money.egg-info/PKG-INFO
python_money.egg-info/SOURCES.txt
python_money.egg-info/dependency_links.txt
python_money.egg-info/top_level.txt
tests/django_test/__init__.py
tests/django_test/manage.py
tests/django_test/models.py
tests/django_test/settings.py
tests/django_test/tests.py
tests/django_test/urls.py
tests/django_test/views.py
tests/django_test/templates/form.html