Metadata-Version: 1.0
Name: python-money
Version: 0.5
Summary: Data classes to represent Money and Currency types
Home-page: http://code.google.com/p/python-money
Author: Ben Coughlan
Author-email: ben.coughlan@gmail.com
License: BSD
Keywords: money currency
Platform: UNKNOWN
Classifier: Development Status :: 4 - Beta
Classifier: Environment :: Plugins
Classifier: Environment :: Other Environment
Classifier: Framework :: Django
Classifier: Operating System :: OS Independent
Classifier: Intended Audience :: Developers
Classifier: Intended Audience :: Financial and Insurance Industry
Classifier: License :: OSI Approved :: BSD License
Classifier: Programming Language :: Python
Classifier: Topic :: Office/Business :: Financial
